asynctools/__init__.py
asynctools/_testutil.py
asynctools/threading/Async.py
asynctools/threading/Parallel.py
asynctools/threading/Pool.py
asynctools/threading/__init__.py
asynctools-0.1.3.dist-info/LICENSE
asynctools-0.1.3.dist-info/METADATA
asynctools-0.1.3.dist-info/WHEEL
asynctools-0.1.3.dist-info/top_level.txt
asynctools-0.1.3.dist-info/RECORD
