Metadata-Version: 2.1
Name: asynctools
Version: 0.1.3
Summary: Async tools for Python 
Home-page: https://github.com/kolypto/py-asynctools
Author: Mark Vartanyan
Author-email: kolypto@gmail.com
License: BSD
Keywords: async,threading,multiprocessing
Platform: any
Classifier: Development Status :: 5 - Production/Stable
Classifier: Intended Audience :: Developers
Classifier: Natural Language :: English
Classifier: Operating System :: OS Independent
Classifier: Programming Language :: Python :: 2
Classifier: Programming Language :: Python :: 3
Classifier: Topic :: Software Development :: Libraries :: Python Modules
